ElegantDevelopment/AWSCDKDynamoDBSeeder/__init__.py
ElegantDevelopment/AWSCDKDynamoDBSeeder/py.typed
ElegantDevelopment/AWSCDKDynamoDBSeeder/_jsii/__init__.py
ElegantDevelopment/AWSCDKDynamoDBSeeder/_jsii/aws-cdk-dynamodb-seeder@1.56.1.jsii.tgz
aws_cdk_dynamodb_seeder-1.56.1.dist-info/METADATA
aws_cdk_dynamodb_seeder-1.56.1.dist-info/WHEEL
aws_cdk_dynamodb_seeder-1.56.1.dist-info/top_level.txt
aws_cdk_dynamodb_seeder-1.56.1.dist-info/RECORD
