Metadata-Version: 2.1
Name: aws-cdk-dynamodb-seeder
Version: 1.56.1
Summary: A simple CDK JSON seeder for DynamoDB
Home-page: https://github.com/elegantdevelopment/aws-cdk-dynamodb-seeder#readme
Author: Justin Taylor<jtaylor@elegantdevelopment.co.uk>
License: Apache-2.0
Project-URL: Source, https://github.com/elegantdevelopment/aws-cdk-dynamodb-seeder.git
Platform: UNKNOWN
Classifier: Intended Audience :: Developers
Classifier: Operating System :: OS Independent
Classifier: Programming Language :: JavaScript
Classifier: Programming Language :: Python :: 3 :: Only
Classifier: Programming Language :: Python :: 3.6
Classifier: Programming Language :: Python :: 3.7
Classifier: Programming Language :: Python :: 3.8
Classifier: Typing :: Typed
Classifier: Development Status :: 4 - Beta
Classifier: License :: OSI Approved
Requires-Python: >=3.6
Requires-Dist: jsii (<2.0.0,>=1.9.0)
Requires-Dist: publication (>=0.0.3)
Requires-Dist: aws-cdk.aws-dynamodb (<2.0.0,>=1.56.0)
Requires-Dist: aws-cdk.aws-lambda (<2.0.0,>=1.56.0)
Requires-Dist: aws-cdk.aws-s3 (<2.0.0,>=1.56.0)
Requires-Dist: aws-cdk.aws-s3-deployment (<2.0.0,>=1.56.0)
Requires-Dist: aws-cdk.core (<2.0.0,>=1.56.0)
Requires-Dist: aws-cdk.custom-resources (<2.0.0,>=1.56.0)
Requires-Dist: constructs (<4.0.0,>=3.0.4)
